use_minimon/__init__.py
use_minimon/flashing.py
use_minimon/flashmap.toml
use_minimon/responder.py
use_minimon_dj-0.1.0.dist-info/LICENSE-APACHE
use_minimon_dj-0.1.0.dist-info/LICENSE-MIT
use_minimon_dj-0.1.0.dist-info/METADATA
use_minimon_dj-0.1.0.dist-info/WHEEL
use_minimon_dj-0.1.0.dist-info/entry_points.txt
use_minimon_dj-0.1.0.dist-info/top_level.txt
use_minimon_dj-0.1.0.dist-info/RECORD
