Metadata-Version: 2.1
Name: use-minimon-dj
Version: 0.1.0
Summary: To make use of Renesas' MiniMonitor
Home-page: https://github.com/djangolyu/useminimon
Author: Djang Lyu
License: UNKNOWN
Project-URL: Bug Tracker, https://github.com/djangolyu/useminimon/issues
Platform: UNKNOWN
Classifier: Development Status :: 3 - Alpha
Classifier: Environment :: Console
Classifier: Intended Audience :: Developers
Classifier: License :: OSI Approved :: Apache Software License
Classifier: License :: OSI Approved :: MIT License
Classifier: Operating System :: POSIX :: Linux
Classifier: Programming Language :: Python :: 3
Requires-Python: >=3.6
License-File: LICENSE-APACHE
License-File: LICENSE-MIT
Requires-Dist: pyserial
Requires-Dist: tqdm
Requires-Dist: toml
Requires-Dist: types-toml
